{"objectID":454003,"isHighlight":false,"accessionNumber":"2000.301","isPublicDomain":true,"primaryImage":"https://images.metmuseum.org/CRDImages/is/original/DP217229.jpg","primaryImageSmall":"https://images.metmuseum.org/CRDImages/is/web-large/DP217229.jpg","additionalImages":["https://images.metmuseum.org/CRDImages/is/original/DP217230.jpg","https://images.metmuseum.org/CRDImages/is/original/DP217231.jpg","https://images.metmuseum.org/CRDImages/is/original/DP217232.jpg","https://images.metmuseum.org/CRDImages/is/original/DP217233.jpg","https://images.metmuseum.org/CRDImages/is/original/DP217236.jpg","https://images.metmuseum.org/CRDImages/is/original/ISL104.jpg","https://images.metmuseum.org/CRDImages/is/original/ISL105.jpg","https://images.metmuseum.org/CRDImages/is/original/DT4682.jpg","https://images.metmuseum.org/CRDImages/is/original/DT4683.jpg","https://images.metmuseum.org/CRDImages/is/original/2000.301.jpg"],"constituents":null,"department":"Islamic Art","objectName":"Box","title":"Inlaid Box for the Portuguese Market","culture":"","period":"","dynasty":"","reign":"","portfolio":"","artistRole":"","artistPrefix":"","artistDisplayName":"","artistDisplayBio":"","artistSuffix":"","artistAlphaSort":"","artistNationality":"","artistBeginDate":"","artistEndDate":"","objectDate":"ca.1600","objectBeginDate":1575,"objectEndDate":1625,"medium":"Wood (teak); veneered with ebony, inlaid ivory, and lac","dimensions":"H. 3 1/4 in. (8.3 cm)\r\nW. 13 1/2 in. (34.3 cm)\r\nD. 5 11/16 in. (14.5 cm)\r\nWt. 40.2 oz. (1139.8 g)","creditLine":"Cynthia Hazen Polsky and Leon B. Polsky Fund, 2000","geographyType":"Probably made in","city":"probably Ahmedabad","state":"","county":"","country":"India","region":"Gujarat","subregion":"","locale":"","locus":"","excavation":"","river":"","classification":"Wood","rightsAndReproduction":"","linkResource":"","metadataDate":"2019-02-01T10:50:49.477Z","repository":"Metropolitan Museum of Art, New York, NY","objectURL":"https://www.metmuseum.org/art/collection/search/454003","tags":["Animals","Men","Hunting","Writing Implements"]}