{"objectID":464495,"isHighlight":false,"accessionNumber":"17.190.53","isPublicDomain":true,"primaryImage":"https://images.metmuseum.org/CRDImages/md/original/DT116.jpg","primaryImageSmall":"https://images.metmuseum.org/CRDImages/md/web-large/DT116.jpg","additionalImages":["https://images.metmuseum.org/CRDImages/md/original/DT2672.jpg"],"constituents":null,"department":"Medieval Art","objectName":"Diptych wing","title":"Panel of a Diptych Announcing the Consulship of Justinian","culture":"Byzantine","period":"","dynasty":"","reign":"","portfolio":"","artistRole":"","artistPrefix":"","artistDisplayName":"","artistDisplayBio":"","artistSuffix":"","artistAlphaSort":"","artistNationality":"","artistBeginDate":"","artistEndDate":"","objectDate":"521","objectBeginDate":521,"objectEndDate":521,"medium":"Ivory","dimensions":"Overall: 13 7/8 x 5 3/8 x 3/8 in. (35.2 x 13.7 x 1 cm)","creditLine":"Gift of J. Pierpont Morgan, 1917","geographyType":"Made in","city":"Constantinople","state":"","county":"","country":"","region":"","subregion":"","locale":"","locus":"","excavation":"","river":"","classification":"Ivories","rightsAndReproduction":"","linkResource":"","metadataDate":"2019-09-07T05:03:09.203Z","repository":"Metropolitan Museum of Art, New York, NY","objectURL":"https://www.metmuseum.org/art/collection/search/464495","tags":["Flowers"]}