{"objectID":474091,"isHighlight":false,"accessionNumber":"25.120.531–.1052","isPublicDomain":true,"primaryImage":"https://images.metmuseum.org/CRDImages/cl/original/DP102892.jpg","primaryImageSmall":"https://images.metmuseum.org/CRDImages/cl/web-large/DP102892.jpg","additionalImages":["https://images.metmuseum.org/CRDImages/cl/original/DP130997.jpg"],"constituents":null,"department":"The Cloisters","objectName":"Cloister","title":"Cloister","culture":"French","period":"","dynasty":"","reign":"","portfolio":"","artistRole":"","artistPrefix":"","artistDisplayName":"","artistDisplayBio":"","artistSuffix":"","artistAlphaSort":"","artistNationality":"","artistBeginDate":"","artistEndDate":"","objectDate":"late 13th–14th century","objectBeginDate":1275,"objectEndDate":1399,"medium":"Marble","dimensions":"Overall: 54 ft. 3 in. x 49 ft. (1,660 x 1,490 cm)","creditLine":"The Cloisters Collection, 1925","geographyType":"Made in","city":"","state":"","county":"","country":"France","region":"Midi-Pyrénées","subregion":"","locale":"","locus":"","excavation":"","river":"","classification":"Sculpture-Architectural","rightsAndReproduction":"","linkResource":"","metadataDate":"2019-02-01T10:50:49.477Z","repository":"Metropolitan Museum of Art, New York, NY","objectURL":"https://www.metmuseum.org/art/collection/search/474091","tags":["Cloisters"]}