{"objectID":50939,"isHighlight":false,"accessionNumber":"1999.148","isPublicDomain":true,"primaryImage":"https://images.metmuseum.org/CRDImages/as/original/DP153182.jpg","primaryImageSmall":"https://images.metmuseum.org/CRDImages/as/web-large/DP153182.jpg","additionalImages":["https://images.metmuseum.org/CRDImages/as/original/LC-1999_148_002.jpg"],"constituents":null,"department":"Asian Art","objectName":"Page","title":"Vasant Ragini, Page from a Ragamala Series (Garland of Musical Modes)","culture":"India (Rajasthan, Amber)","period":"","dynasty":"","reign":"","portfolio":"","artistRole":"","artistPrefix":"","artistDisplayName":"","artistDisplayBio":"","artistSuffix":"","artistAlphaSort":"","artistNationality":"","artistBeginDate":"","artistEndDate":"","objectDate":"early 17th century","objectBeginDate":1600,"objectEndDate":1633,"medium":"Ink, opaque watercolor, and gold on paper","dimensions":"9 13/16 x 7 7/8 in. (24.9 x 20 cm)","creditLine":"Friends of Asian Art, Purchase, Mr. and Mrs. Andrew Saul Gift, 1999","geographyType":"","city":"","state":"","county":"","country":"","region":"","subregion":"","locale":"","locus":"","excavation":"","river":"","classification":"Paintings","rightsAndReproduction":"","linkResource":"","metadataDate":"","repository":"Metropolitan Museum of Art, New York, NY","objectURL":"https://www.metmuseum.org/art/collection/search/50939","tags":[]}