{"objectID":53414,"isHighlight":false,"accessionNumber":"2015.300.286a–h","isPublicDomain":true,"primaryImage":"https://images.metmuseum.org/CRDImages/as/original/2015_300_286ah_O_Burke_website.jpg","primaryImageSmall":"https://images.metmuseum.org/CRDImages/as/web-large/2015_300_286ah_O_Burke_website.jpg","additionalImages":["https://images.metmuseum.org/CRDImages/as/original/2015_300_286a_h_Int_Burke.jpg"],"constituents":null,"department":"Asian Art","objectName":"Writing box","title":"Writing Box (Suzuribako) with “Dream in Naniwa” Design","culture":"Japan","period":"Edo period (1615–1868)","dynasty":"","reign":"","portfolio":"","artistRole":"","artistPrefix":"","artistDisplayName":"","artistDisplayBio":"","artistSuffix":"","artistAlphaSort":"","artistNationality":"","artistBeginDate":"","artistEndDate":"","objectDate":"18th century","objectBeginDate":1550,"objectEndDate":1850,"medium":"Lacquered wood with gold, silver takamaki-e, hiramaki-e, and silver inlay","dimensions":"H. 2 1/8 in. (5.4 cm); W. 9 1/2 in. (24.1 cm); L. 9 1/4 in. (23.5 cm)","creditLine":"Mary Griggs Burke Collection, Gift of the Mary and Jackson Burke Foundation, 2015","geographyType":"","city":"","state":"","county":"","country":"","region":"","subregion":"","locale":"","locus":"","excavation":"","river":"","classification":"Lacquer","rightsAndReproduction":"","linkResource":"","metadataDate":"2019-02-01T10:50:49.477Z","repository":"Metropolitan Museum of Art, New York, NY","objectURL":"https://www.metmuseum.org/art/collection/search/53414","tags":["Writing Implements"]}