{"objectID":670886,"isHighlight":false,"accessionNumber":"2015.300.23","isPublicDomain":true,"primaryImage":"https://images.metmuseum.org/CRDImages/as/original/DP-12232-020.jpg","primaryImageSmall":"https://images.metmuseum.org/CRDImages/as/web-large/DP-12232-020.jpg","additionalImages":["https://images.metmuseum.org/CRDImages/as/original/DP-12232-019.jpg"],"constituents":null,"department":"Asian Art","objectName":"Hanging scroll","title":"Ariwara Narihira (825–880), from the Fujifusa version of Thirty-six Immortal Poets","culture":"Japan","period":"Muromachi period (1392–1573)","dynasty":"","reign":"","portfolio":"","artistRole":"","artistPrefix":"","artistDisplayName":"","artistDisplayBio":"","artistSuffix":"","artistAlphaSort":"","artistNationality":"","artistBeginDate":"","artistEndDate":"","objectDate":"first half of the15th century","objectBeginDate":1400,"objectEndDate":1449,"medium":"Hanging scroll; ink and color on paper","dimensions":"Image: 9 13/16 × 17 15/16 in. (25 × 45.5 cm)\r\nOverall with mounting: 41 9/16 × 22 5/8 in. (105.5 × 57.4 cm)\r\nOverall with knobs: 41 9/16 × 24 5/16 in. (105.5 × 61.8 cm)","creditLine":"Mary Griggs Burke Collection, Gift of the Mary and Jackson Burke Foundation, 2015","geographyType":"","city":"","state":"","county":"","country":"","region":"","subregion":"","locale":"","locus":"","excavation":"","river":"","classification":"Paintings","rightsAndReproduction":"","linkResource":"","metadataDate":"2019-08-06T04:38:15.95Z","repository":"Metropolitan Museum of Art, New York, NY","objectURL":"https://www.metmuseum.org/art/collection/search/670886","tags":["Poetry","Men"]}