{"objectID":236575,"isHighlight":false,"accessionNumber":"2008.543.6, .7","isPublicDomain":true,"primaryImage":"https://images.metmuseum.org/CRDImages/es/original/DP169330.jpg","primaryImageSmall":"https://images.metmuseum.org/CRDImages/es/web-large/DP169330.jpg","additionalImages":["https://images.metmuseum.org/CRDImages/es/original/SF2008_543_6,7.jpg","https://images.metmuseum.org/CRDImages/es/original/SF2008_543_6_img2.jpg","https://images.metmuseum.org/CRDImages/es/original/SF2008_543_7_img5.jpg"],"constituents":null,"department":"European Sculpture and Decorative Arts","objectName":"Vases","title":"Pair of mounted vases","culture":"","period":"","dynasty":"","reign":"","portfolio":"","artistRole":"","artistPrefix":"","artistDisplayName":"","artistDisplayBio":"","artistSuffix":"","artistAlphaSort":"","artistNationality":"","artistBeginDate":"","artistEndDate":"","objectDate":"porcelain early 18th century, mounts ca. 1765","objectBeginDate":1700,"objectEndDate":1770,"medium":"Chinese porcelain; gilt-bronze mounts","dimensions":"Overall (confirmed): H. 12-3/8 x W. 7-3/4 x D. 7 in. (31.4 x 19.7 x 17.8 cm)","creditLine":"Gift of Mrs. Charles Wrightsman, 2008","geographyType":"","city":"","state":"","county":"","country":"","region":"","subregion":"","locale":"","locus":"","excavation":"","river":"","classification":"Ceramics-Porcelain","rightsAndReproduction":"","linkResource":"","metadataDate":"2019-05-22T03:00:45.347Z","repository":"Metropolitan Museum of Art, New York, NY","objectURL":"https://www.metmuseum.org/art/collection/search/236575","tags":["Butterflies"]}