{"objectID":312256,"isHighlight":false,"accessionNumber":"1979.206.768","isPublicDomain":true,"primaryImage":"https://images.metmuseum.org/CRDImages/ao/original/1979.206.768_a.jpg","primaryImageSmall":"https://images.metmuseum.org/CRDImages/ao/web-large/1979.206.768_a.jpg","additionalImages":["https://images.metmuseum.org/CRDImages/ao/original/1979.206.768_b.jpg"],"constituents":null,"department":"Arts of Africa, Oceania, and the Americas","objectName":"Ocarina","title":"Ocarina","culture":"Guanacaste-Nicoya","period":"","dynasty":"","reign":"","portfolio":"","artistRole":"","artistPrefix":"","artistDisplayName":"","artistDisplayBio":"","artistSuffix":"","artistAlphaSort":"","artistNationality":"","artistBeginDate":"","artistEndDate":"","objectDate":"9th–12th century","objectBeginDate":800,"objectEndDate":1200,"medium":"Ceramic, pigment","dimensions":"H. 2 3/8 x W. 2 3/8 x D. 4 5/8 in. (6.1 x 6.1 x 11.7 cm)","creditLine":"The Michael C. Rockefeller Memorial Collection, Bequest of Nelson A. Rockefeller, 1979","geographyType":"","city":"","state":"","county":"","country":"Costa Rica","region":"","subregion":"","locale":"","locus":"","excavation":"","river":"","classification":"Ceramics-Musical Instruments","rightsAndReproduction":"","linkResource":"","metadataDate":"2019-02-01T10:50:49.477Z","repository":"Metropolitan Museum of Art, New York, NY","objectURL":"https://www.metmuseum.org/art/collection/search/312256","tags":["Musical Instruments"]}