{"objectID":500759,"isHighlight":false,"accessionNumber":"89.4.190","isPublicDomain":true,"primaryImage":"https://images.metmuseum.org/CRDImages/mi/original/MIDP89.4.190.jpg","primaryImageSmall":"https://images.metmuseum.org/CRDImages/mi/web-large/MIDP89.4.190.jpg","additionalImages":["https://images.metmuseum.org/CRDImages/mi/original/MUS183Aleft.jpg"],"constituents":null,"department":"Musical Instruments","objectName":"Sitar","title":"Sitar","culture":"Indian","period":"","dynasty":"","reign":"","portfolio":"","artistRole":"","artistPrefix":"","artistDisplayName":"","artistDisplayBio":"","artistSuffix":"","artistAlphaSort":"","artistNationality":"","artistBeginDate":"","artistEndDate":"","objectDate":"mid-19th century","objectBeginDate":1830,"objectEndDate":1870,"medium":"Wood","dimensions":"53 1/2 × 14 13/16 × 3 1/2 in. (135.9 × 37.6 × 8.9 cm)","creditLine":"The Crosby Brown Collection of Musical Instruments, 1889","geographyType":"","city":"","state":"","county":"","country":"India","region":"","subregion":"","locale":"","locus":"","excavation":"","river":"","classification":"Chordophone-Lute-plucked-fretted","rightsAndReproduction":"","linkResource":"","metadataDate":"2019-07-26T03:00:41.71Z","repository":"Metropolitan Museum of Art, New York, NY","objectURL":"https://www.metmuseum.org/art/collection/search/500759","tags":[]}