{"objectID":501492,"isHighlight":true,"accessionNumber":"89.4.881a–c","isPublicDomain":true,"primaryImage":"https://images.metmuseum.org/CRDImages/mi/original/DP147202.jpg","primaryImageSmall":"https://images.metmuseum.org/CRDImages/mi/web-large/DP147202.jpg","additionalImages":[],"constituents":null,"department":"Musical Instruments","objectName":"Sea Dragon","title":"Sea Dragon","culture":"Italian","period":"","dynasty":"","reign":"","portfolio":"","artistRole":"","artistPrefix":"","artistDisplayName":"","artistDisplayBio":"","artistSuffix":"","artistAlphaSort":"","artistNationality":"","artistBeginDate":"","artistEndDate":"","objectDate":"17th century","objectBeginDate":1700,"objectEndDate":1799,"medium":"Wood, brass, gilding","dimensions":"Height: 54 1/2 in. (138.4 cm)\r\nWidth: 8 in. (20.3 cm)\r\nDepth: 3 1/2 in. (8.9 cm)","creditLine":"The Crosby Brown Collection of Musical Instruments, 1889","geographyType":"","city":"","state":"","county":"","country":"Italy","region":"","subregion":"","locale":"","locus":"","excavation":"","river":"","classification":"Aerophone-Reed Vibrated-double reed","rightsAndReproduction":"","linkResource":"","metadataDate":"2019-07-26T03:00:41.71Z","repository":"Metropolitan Museum of Art, New York, NY","objectURL":"https://www.metmuseum.org/art/collection/search/501492","tags":["Dragons"]}