{"objectID":502325,"isHighlight":true,"accessionNumber":"89.4.1778","isPublicDomain":true,"primaryImage":"https://images.metmuseum.org/CRDImages/mi/original/DT10869.jpg","primaryImageSmall":"https://images.metmuseum.org/CRDImages/mi/web-large/DT10869.jpg","additionalImages":[],"constituents":null,"department":"Musical Instruments","objectName":"Rectangular Octave Virginal","title":"Rectangular Octave Virginal","culture":"German","period":"","dynasty":"","reign":"","portfolio":"","artistRole":"","artistPrefix":"","artistDisplayName":"","artistDisplayBio":"","artistSuffix":"","artistAlphaSort":"","artistNationality":"","artistBeginDate":"","artistEndDate":"","objectDate":"ca. 1600","objectBeginDate":1580,"objectEndDate":1620,"medium":"Ebony, beech, brass, leather, paper, parchment, ivory","dimensions":"Height: 3 9/16 in. (9.1 cm)\r\nWidth (parallel to keyboard): 17 3/8 in. (44.1 cm)\r\nDepth (perpendicular to keyboard): 8 9/16 in. (21.8 cm)","creditLine":"The Crosby Brown Collection of Musical Instruments, 1889","geographyType":"","city":"Possibly Augsburg","state":"","county":"","country":"Germany","region":"","subregion":"","locale":"","locus":"","excavation":"","river":"","classification":"Chordophone-Zither-plucked-virginal","rightsAndReproduction":"","linkResource":"","metadataDate":"2019-02-14T04:42:47.037Z","repository":"Metropolitan Museum of Art, New York, NY","objectURL":"https://www.metmuseum.org/art/collection/search/502325","tags":["Men","Women","Dogs","Dining"]}