{"objectID":229640,"isHighlight":false,"accessionNumber":"1979.311.5","isPublicDomain":true,"primaryImage":"https://images.metmuseum.org/CRDImages/es/original/225880.jpg","primaryImageSmall":"https://images.metmuseum.org/CRDImages/es/web-large/225880.jpg","additionalImages":[],"constituents":null,"department":"European Sculpture and Decorative Arts","objectName":"Edging","title":"Edging","culture":"","period":"","dynasty":"","reign":"","portfolio":"","artistRole":"","artistPrefix":"","artistDisplayName":"","artistDisplayBio":"","artistSuffix":"","artistAlphaSort":"","artistNationality":"","artistBeginDate":"","artistEndDate":"","objectDate":"mid-18th century","objectBeginDate":1730,"objectEndDate":1765,"medium":"Bobbin lace, Brussels lace, point d'Angleterre, linen","dimensions":"L. 60 1/2 x W. 2 1/2 inches (153.7 x 6.4 cm)","creditLine":"Gift of Mrs. Donald P. Spence in memory of her mother Mrs. William Redmond Cross, 1979","geographyType":"","city":"","state":"","county":"","country":"","region":"","subregion":"","locale":"","locus":"","excavation":"","river":"","classification":"Textiles-Laces","rightsAndReproduction":"","linkResource":"","metadataDate":"2019-04-27T03:00:45.603Z","repository":"Metropolitan Museum of Art, New York, NY","objectURL":"https://www.metmuseum.org/art/collection/search/229640","tags":["Flowers"]}