{"objectID":320962,"isHighlight":false,"accessionNumber":"2012.5","isPublicDomain":true,"primaryImage":"https://images.metmuseum.org/CRDImages/ao/original/TR.397.2.2011a.JPG","primaryImageSmall":"https://images.metmuseum.org/CRDImages/ao/web-large/TR.397.2.2011a.JPG","additionalImages":["https://images.metmuseum.org/CRDImages/ao/original/DP326510.jpg","https://images.metmuseum.org/CRDImages/ao/original/DP326502.jpg","https://images.metmuseum.org/CRDImages/ao/original/DP326511.jpg","https://images.metmuseum.org/CRDImages/ao/original/DP326509.jpg","https://images.metmuseum.org/CRDImages/ao/original/TR.397.2.2011 b.JPG","https://images.metmuseum.org/CRDImages/ao/original/TR.397.2.2011 c.JPG","https://images.metmuseum.org/CRDImages/ao/original/TR.397.2.2011 e.JPG","https://images.metmuseum.org/CRDImages/ao/original/TR.397.2.2011 f.JPG","https://images.metmuseum.org/CRDImages/ao/original/TR.397.2.2011 g.JPG","https://images.metmuseum.org/CRDImages/ao/original/TR.397.2.2011 h.JPG"],"constituents":null,"department":"Arts of Africa, Oceania, and the Americas","objectName":"Scroll","title":"Healing Scroll","culture":"Tigrinya peoples","period":"","dynasty":"","reign":"","portfolio":"","artistRole":"","artistPrefix":"","artistDisplayName":"","artistDisplayBio":"","artistSuffix":"","artistAlphaSort":"","artistNationality":"","artistBeginDate":"","artistEndDate":"","objectDate":"18th–19th century","objectBeginDate":1700,"objectEndDate":1897,"medium":"Parchment, ink, pigments, cotton","dimensions":"L. 75 9/16 x W. 6 11/16 in. (192 x 17 cm)","creditLine":"Purchase, Marie Sussek Gift, 2012","geographyType":"","city":"","state":"","county":"","country":"Ethiopia","region":"Tigray region","subregion":"","locale":"","locus":"","excavation":"","river":"","classification":"Parchment","rightsAndReproduction":"","linkResource":"","metadataDate":"2019-02-01T10:50:49.477Z","repository":"Metropolitan Museum of Art, New York, NY","objectURL":"https://www.metmuseum.org/art/collection/search/320962","tags":["Scrolls","Faces"]}