{"objectID":324008,"isHighlight":true,"accessionNumber":"43.135.2","isPublicDomain":true,"primaryImage":"https://images.metmuseum.org/CRDImages/an/original/DP-16679-001.jpg","primaryImageSmall":"https://images.metmuseum.org/CRDImages/an/web-large/DP-16679-001.jpg","additionalImages":["https://images.metmuseum.org/CRDImages/an/original/DP-16679-002.jpg","https://images.metmuseum.org/CRDImages/an/original/DP-16679-003.jpg"],"constituents":null,"department":"Ancient Near Eastern Art","objectName":"Relief","title":"Orthostat relief: lion-hunt scene","culture":"Hittite","period":"Neo-Hittite","dynasty":"","reign":"","portfolio":"","artistRole":"","artistPrefix":"","artistDisplayName":"","artistDisplayBio":"","artistSuffix":"","artistAlphaSort":"","artistNationality":"","artistBeginDate":"","artistEndDate":"","objectDate":"ca. 10th−9th century B.C.","objectBeginDate":-1000,"objectEndDate":-800,"medium":"Basalt","dimensions":"22 1/16 × 8 7/16 × 27 3/16 in., 434 lb. (56 × 21.5 × 69 cm)","creditLine":"Rogers Fund, 1943","geographyType":"","city":"","state":"","county":"","country":"","region":"Syria","subregion":"Tell Halaf (ancient Guzana)","locale":"","locus":"","excavation":"","river":"","classification":"Stone-Reliefs-Inscribed","rightsAndReproduction":"","linkResource":"","metadataDate":"2019-11-01T04:43:23.86Z","repository":"Metropolitan Museum of Art, New York, NY","objectURL":"https://www.metmuseum.org/art/collection/search/324008","tags":["Birds","Hunting","Horses","Chariots","Lions"]}