{"objectID":466096,"isHighlight":true,"accessionNumber":"1982.432","isPublicDomain":true,"primaryImage":"https://images.metmuseum.org/CRDImages/cl/original/CT_21130.jpg","primaryImageSmall":"https://images.metmuseum.org/CRDImages/cl/web-large/CT_21130.jpg","additionalImages":[],"constituents":null,"department":"The Cloisters","objectName":"Textile","title":"Opus Anglicanum (Chasuble)","culture":"British","period":"","dynasty":"","reign":"","portfolio":"","artistRole":"","artistPrefix":"","artistDisplayName":"","artistDisplayBio":"","artistSuffix":"","artistAlphaSort":"","artistNationality":"","artistBeginDate":"","artistEndDate":"","objectDate":"late 15th century","objectBeginDate":1450,"objectEndDate":1499,"medium":"Silk and metallic threads on linen; appliqué on silk velvet foundation with silk embroidery and silver-gilt shot","dimensions":"28 3/4 x 14 3/16 in. (73 x 36 cm)","creditLine":"The Cloisters Collection, 1982","geographyType":"","city":"","state":"","county":"","country":"","region":"","subregion":"","locale":"","locus":"","excavation":"","river":"","classification":"Textiles-Embroidered","rightsAndReproduction":"","linkResource":"","metadataDate":"2019-10-17T04:46:24.823Z","repository":"Metropolitan Museum of Art, New York, NY","objectURL":"https://www.metmuseum.org/art/collection/search/466096","tags":["Angels","Vestments"]}