{"objectID":26565,"isHighlight":false,"accessionNumber":"2000.66a–c","isPublicDomain":true,"primaryImage":"https://images.metmuseum.org/CRDImages/aa/original/DT9191.jpg","primaryImageSmall":"https://images.metmuseum.org/CRDImages/aa/web-large/DT9191.jpg","additionalImages":[],"constituents":null,"department":"Arms and Armor","objectName":"Scale armor","title":"Scale Armor","culture":"Subeixi or Scythian","period":"","dynasty":"","reign":"","portfolio":"","artistRole":"","artistPrefix":"","artistDisplayName":"","artistDisplayBio":"","artistSuffix":"","artistAlphaSort":"","artistNationality":"","artistBeginDate":"","artistEndDate":"","objectDate":"8th–3rd century B.C.","objectBeginDate":-799,"objectEndDate":-200,"medium":"Leather, pigments","dimensions":"H. 27 3/4 in. (70.5 cm); W. at shoulders 15 3/4 in. (40 cm)","creditLine":"Purchase, Arthur Ochs Sulzberger Gift, 2000","geographyType":"Country of Origin","city":"","state":"","county":"","country":"","region":"Central Asia","subregion":"","locale":"","locus":"","excavation":"","river":"","classification":"Armor for Man","rightsAndReproduction":"","linkResource":"","metadataDate":"2019-07-21T03:00:42.11Z","repository":"Metropolitan Museum of Art, New York, NY","objectURL":"https://www.metmuseum.org/art/collection/search/26565","tags":[]}