[{"decades":"before1000","artworks":[{"filename":"740_DP153705.jpg","colorValue":[29,25,49]}]},{"decades":"1000-1199","artworks":[{"filename":"1000_DP164581.jpg","colorValue":[29,23,60]},{"filename":"1156_DP165265_CRD.jpg","colorValue":[31,33,33]},{"filename":"1100_DP154079.jpg","colorValue":[35,27,27]},{"filename":"1160_DP-15820-005_crd.jpg","colorValue":[35,20,35]}]},{"decades":"1200-1399","artworks":[{"filename":"1317_DP168805.jpg","colorValue":[21,49,32]},{"filename":"1287_DP258037.jpg","colorValue":[23,22,43]},{"filename":"1336_DP276268.jpg","colorValue":[25,29,29]},{"filename":"1336_DP276277.jpg","colorValue":[25,29,30]},{"filename":"1336_DP276266.jpg","colorValue":[26,28,31]},{"filename":"1317_DP-12431-001.jpg","colorValue":[26,27,20]},{"filename":"1300_DT215134.jpg","colorValue":[27,30,44]},{"filename":"1333_DP-13336-001.jpg","colorValue":[27,34,43]},{"filename":"1367_DP221038.jpg","colorValue":[27,30,28]},{"filename":"1327_DP-13337-001.jpg","colorValue":[27,38,38]},{"filename":"1368_47_18_105_d.jpg","colorValue":[27,12,50]},{"filename":"1340_DT4166.jpg","colorValue":[27,59,38]},{"filename":"1327_DP-13338-001.jpg","colorValue":[28,43,35]},{"filename":"1300_DP154100.jpg","colorValue":[28,31,32]},{"filename":"1200_DP165233_CRD.jpg","colorValue":[29,22,39]},{"filename":"1310_DP270170.jpg","colorValue":[29,32,62]},{"filename":"1267_DP152422_CRD.jpg","colorValue":[29,39,35]},{"filename":"1317_DP168803.jpg","colorValue":[30,21,16]},{"filename":"1360_DP213279_CRD.jpg","colorValue":[30,15,49]},{"filename":"1335_DT8082.jpg","colorValue":[30,46,28]},{"filename":"1334_DP215096.jpg","colorValue":[30,33,37]},{"filename":"1336_DP231181.jpg","colorValue":[30,34,35]},{"filename":"1296_DP213981_CRD.jpg","colorValue":[31,26,67]},{"filename":"1336_DP221032.jpg","colorValue":[31,32,30]},{"filename":"1300_DP700723.jpg","colorValue":[31,28,53]},{"filename":"1200_DP153509.jpg","colorValue":[31,26,41]},{"filename":"1267_DP244667_CRD.jpg","colorValue":[31,26,56]},{"filename":"1368_DP153573.jpg","colorValue":[32,31,58]},{"filename":"1368_EP270.jpg","colorValue":[32,41,54]},{"filename":"1345_DP367960.jpg","colorValue":[33,50,54]},{"filename":"1340_DP153818.jpg","colorValue":[33,36,40]},{"filename":"1318_DT215.jpg","colorValue":[33,46,36]},{"filename":"1200_47_18_136_O2_sf.jpg","colorValue":[34,22,58]},{"filename":"1336_DP276272.jpg","colorValue":[34,30,63]},{"filename":"1367_DP235486.jpg","colorValue":[34,25,58]},{"filename":"1267_DP153531.jpg","colorValue":[35,53,82]},{"filename":"1343_DT2770.jpg","colorValue":[36,54,37]},{"filename":"1222_DP-13993-003.jpg","colorValue":[36,12,51]},{"filename":"1339_DT6289.jpg","colorValue":[37,19,55]},{"filename":"1359_DP224544.jpg","colorValue":[38,28,69]},{"filename":"1317_DP168806.jpg","colorValue":[38,56,55]},{"filename":"1200_DP235005_CRD.jpg","colorValue":[39,32,75]},{"filename":"1367_DT5220.jpg","colorValue":[43,17,33]},{"filename":"1335_SF Maso.jpg","colorValue":[45,50,38]},{"filename":"1336_DT209331.jpg","colorValue":[45,26,28]}]},{"decades":"1400-1599","artworks":[{"filename":"1500_ep05.2.1.bw.R.jpg","colorValue":[0,0,30]},{"filename":"1426_ep43.98.2.bw.R.jpg","colorValue":[0,0,72]},{"filename":"1540_ep69.282.bw.R.jpg","colorValue":[0,0,11]},{"filename":"1520_ep30.95.258.bw.R.jpg","colorValue":[0,0,19]},{"filename":"1540_DP349558.jpg","colorValue":[12,23,9]},{"filename":"1507_DT11627.jpg","colorValue":[15,9,18]},{"filename":"1515_DT8849.jpg","colorValue":[15,21,15]},{"filename":"1481_DP-17311-001.jpg","colorValue":[17,53,33]},{"filename":"1589_DT209385.jpg","colorValue":[18,19,10]},{"filename":"1485_DT10252.jpg","colorValue":[19,57,34]},{"filename":"1465_DP240360.jpg","colorValue":[19,19,17]},{"filename":"1480_DT712.jpg","colorValue":[20,44,37]},{"filename":"1475_DT1381.jpg","colorValue":[21,14,44]},{"filename":"1577_DT216453.jpg","colorValue":[22,18,21]},{"filename":"1483_DT1369.jpg","colorValue":[22,30,34]},{"filename":"1510_DP102382.jpg","colorValue":[22,9,53]},{"filename":"1465_DP120669.jpg","colorValue":[23,25,6]},{"filename":"1435_DP159891.jpg","colorValue":[23,41,19]},{"filename":"1595_DT10776.jpg","colorValue":[23,35,13]},{"filename":"1449_DP213853.jpg","colorValue":[24,41,16]},{"filename":"1415_DT224129.jpg","colorValue":[25,20,68]},{"filename":"1587_DP243404.jpg","colorValue":[26,24,17]},{"filename":"1459_DT7223.jpg","colorValue":[27,20,22]},{"filename":"1472_DT354152.jpg","colorValue":[27,31,7]},{"filename":"1577_DT4635.jpg","colorValue":[27,40,17]},{"filename":"1597_DP-687-001.jpg","colorValue":[27,42,14]},{"filename":"1491_DT1452.jpg","colorValue":[27,21,8]},{"filename":"1425_DP368622.jpg","colorValue":[27,31,38]},{"filename":"1595_DT11343.jpg","colorValue":[28,22,13]},{"filename":"1570_DP324745.jpg","colorValue":[28,37,63]},{"filename":"1485_DP231371.jpg","colorValue":[28,17,39]},{"filename":"1506_DT7237.jpg","colorValue":[28,28,18]},{"filename":"1497_CT_2902_2.jpg","colorValue":[28,32,44]},{"filename":"1517_DP280366.jpg","colorValue":[28,24,12]},{"filename":"1444_LC-1975_1_070a-001.jpg","colorValue":[28,18,31]},{"filename":"1455_DT1481.jpg","colorValue":[29,43,57]},{"filename":"1512_DP807715.jpg","colorValue":[29,49,81]},{"filename":"1560_DT5111.jpg","colorValue":[29,43,19]},{"filename":"1495_DT1484.jpg","colorValue":[29,37,19]},{"filename":"1536_DP-13665-023.jpg","colorValue":[29,27,35]},{"filename":"1441_DP276260.jpg","colorValue":[29,20,34]},{"filename":"1553_DT382.jpg","colorValue":[29,25,18]},{"filename":"1545_DP811554.jpg","colorValue":[29,34,37]},{"filename":"1400_DP-1488-002.jpg","colorValue":[30,20,20]},{"filename":"1595_DP800082.jpg","colorValue":[30,52,82]},{"filename":"1487_DT3050.jpg","colorValue":[30,43,38]},{"filename":"1597_DT206354.jpg","colorValue":[30,36,42]},{"filename":"1491_DT2649.jpg","colorValue":[30,43,32]},{"filename":"1420_DT9341.jpg","colorValue":[30,38,39]},{"filename":"1400_DP205315_CRD.jpg","colorValue":[30,29,35]},{"filename":"1433_DT273088.jpg","colorValue":[30,33,50]},{"filename":"1594_DT9442.jpg","colorValue":[30,24,19]},{"filename":"1472_DT1453.jpg","colorValue":[30,37,38]},{"filename":"1500_DP280389.jpg","colorValue":[30,27,22]},{"filename":"1550_DP801804.jpg","colorValue":[31,30,70]},{"filename":"1475_DP810666.jpg","colorValue":[31,36,66]},{"filename":"1481_DT8828.jpg","colorValue":[31,53,18]},{"filename":"1475_DP810667.jpg","colorValue":[31,37,66]},{"filename":"1508_DP862672.jpg","colorValue":[31,21,66]},{"filename":"1450_DP161261.jpg","colorValue":[31,35,59]},{"filename":"1500_DP801919.jpg","colorValue":[31,47,84]},{"filename":"1515_DP811752.jpg","colorValue":[31,25,41]},{"filename":"1500_DP801944.jpg","colorValue":[31,29,68]},{"filename":"1500_DP204373_CRD.jpg","colorValue":[31,13,55]},{"filename":"1447_DP247059.jpg","colorValue":[31,48,56]},{"filename":"1400_DP213003_CRD.jpg","colorValue":[31,24,42]},{"filename":"1470_DT7231.jpg","colorValue":[32,36,32]},{"filename":"1500_DP215116.jpg","colorValue":[32,29,57]},{"filename":"1596_DP145411.jpg","colorValue":[32,25,15]},{"filename":"1585_DP-16368-003.jpg","colorValue":[32,43,71]},{"filename":"1450_DP213831.jpg","colorValue":[32,30,18]},{"filename":"1457_DP810259.jpg","colorValue":[32,33,75]},{"filename":"1459_DP104372.jpg","colorValue":[32,24,21]},{"filename":"1470_DT226950.jpg","colorValue":[32,41,38]},{"filename":"1520_DP-17629-001.jpg","colorValue":[32,32,9]},{"filename":"1485_DP296427.jpg","colorValue":[32,13,20]},{"filename":"1499_DP136373.jpg","colorValue":[32,25,32]},{"filename":"1548_DP809499.jpg","colorValue":[33,35,75]},{"filename":"1560_DP361140.jpg","colorValue":[33,27,53]},{"filename":"1460_DP-16339-001.jpg","colorValue":[33,19,20]},{"filename":"1444_LC-1975_1_070b-001.jpg","colorValue":[34,22,55]},{"filename":"1425_DT8826.jpg","colorValue":[34,31,47]},{"filename":"1433_DT2597.jpg","colorValue":[34,32,35]},{"filename":"1467_DP-12232-035.jpg","colorValue":[34,28,50]},{"filename":"1475_DT1356.jpg","colorValue":[34,27,36]},{"filename":"1519_DP-17778-001.jpg","colorValue":[34,12,12]},{"filename":"1520_DP811067.jpg","colorValue":[34,16,56]},{"filename":"1472_DT8827.jpg","colorValue":[34,55,32]},{"filename":"1440_DP161259.jpg","colorValue":[34,7,19]},{"filename":"1565_DP119115.jpg","colorValue":[34,38,43]},{"filename":"1576_DP801722.jpg","colorValue":[34,31,66]},{"filename":"1534_DP251149.jpg","colorValue":[34,29,58]},{"filename":"1550_2015_300_87_d1_Burke_website.jpg","colorValue":[34,33,62]},{"filename":"1534_DP164851.jpg","colorValue":[35,25,46]},{"filename":"1465_DT229155.jpg","colorValue":[35,31,47]},{"filename":"1509_DT11782.jpg","colorValue":[35,32,12]},{"filename":"1560_DP239507.jpg","colorValue":[35,26,17]},{"filename":"1476_DT383.jpg","colorValue":[35,51,38]},{"filename":"1527_DP164800.jpg","colorValue":[36,29,13]},{"filename":"1523_DT6599.jpg","colorValue":[36,45,9]},{"filename":"1500_DT1459.jpg","colorValue":[36,38,45]},{"filename":"1501_DP102196~1.jpg","colorValue":[36,25,67]},{"filename":"1433_DT273089.jpg","colorValue":[36,41,37]},{"filename":"1523_DP295025.jpg","colorValue":[37,26,14]},{"filename":"1480_DT1465.jpg","colorValue":[37,24,15]},{"filename":"1445_DT1479.jpg","colorValue":[37,39,19]},{"filename":"1507_Bonifazio.jpg","colorValue":[37,37,59]},{"filename":"1445_DT1480.jpg","colorValue":[38,30,16]},{"filename":"1570_DP167124.jpg","colorValue":[38,27,14]},{"filename":"1544_DP-17625-001.jpg","colorValue":[39,19,18]},{"filename":"1505_DP807717.jpg","colorValue":[41,25,74]},{"filename":"1505_DP807718.jpg","colorValue":[41,23,73]},{"filename":"1440_DP-17016-001.jpg","colorValue":[42,26,15]},{"filename":"1502_EP14.jpg","colorValue":[45,36,78]},{"filename":"1470_DP250560.jpg","colorValue":[45,9,18]},{"filename":"1505_DP807716.jpg","colorValue":[45,9,57]},{"filename":"1500_DP158827.jpg","colorValue":[45,18,51]},{"filename":"1536_DP802135.jpg","colorValue":[47,8,51]},{"filename":"1597_DT8854.jpg","colorValue":[47,47,6]},{"filename":"1535_DP838058.jpg","colorValue":[48,7,56]},{"filename":"1460_DT7219.jpg","colorValue":[49,9,44]},{"filename":"1512_DT5549.jpg","colorValue":[49,15,14]},{"filename":"1478_2000.664_detail.jpg","colorValue":[49,17,74]},{"filename":"1510_DP-17396-001.jpg","colorValue":[55,17,13]},{"filename":"1503_DP-17398-001.jpg","colorValue":[66,12,16]},{"filename":"1500_DP164819.jpg","colorValue":[80,19,16]},{"filename":"1557_DP105661.jpg","colorValue":[120,3,29]},{"filename":"1536_DP280854.jpg","colorValue":[137,12,11]},{"filename":"1569_DT1483.jpg","colorValue":[197,14,25]},{"filename":"1526_DT5275.jpg","colorValue":[300,1,16]},{"filename":"1499_DT13.jpg","colorValue":[330,3,14]}]},{"decades":"1600-1799","artworks":[{"filename":"1650_DT1347.jpg","colorValue":[0,0,8]},{"filename":"1798_ap60.44.4.jpg","colorValue":[0,0,79]},{"filename":"1600_ep42.23.1.bw.R.jpg","colorValue":[0,0,75]},{"filename":"1771_14_76_55.JPG","colorValue":[0,0,66]},{"filename":"1615_36_100_61_108881.jpg","colorValue":[0,0,70]},{"filename":"1798_ap60.44.6.jpg","colorValue":[0,0,82]},{"filename":"1688_EP542.jpg","colorValue":[0,6,22]},{"filename":"1617_DT251482.jpg","colorValue":[4,30,9]},{"filename":"1648_DT16.jpg","colorValue":[9,9,15]},{"filename":"1670_DP-15413-001.jpg","colorValue":[10,34,13]},{"filename":"1650_DT2819.jpg","colorValue":[15,5,16]},{"filename":"1746_DP214443.jpg","colorValue":[15,71,12]},{"filename":"1657_1972_278_4_O.JPG","colorValue":[15,6,73]},{"filename":"1656_DP355525.jpg","colorValue":[17,25,11]},{"filename":"1605_DP133560.jpg","colorValue":[18,30,22]},{"filename":"1622_DP-17538-001.jpg","colorValue":[18,65,8]},{"filename":"1615_ep51.33.1.R.jpg","colorValue":[18,43,14]},{"filename":"1611_DP261342.jpg","colorValue":[19,24,18]},{"filename":"1663_DP277246.jpg","colorValue":[19,26,16]},{"filename":"1654_DP121330.jpg","colorValue":[20,33,7]},{"filename":"1632_DP143168.jpg","colorValue":[20,5,12]},{"filename":"1630_DT4532.jpg","colorValue":[20,36,13]},{"filename":"1642_DP323414.jpg","colorValue":[20,29,8]},{"filename":"1608_ep55.135.1.R.jpg","colorValue":[21,40,14]},{"filename":"1649_DT1387.jpg","colorValue":[21,59,11]},{"filename":"1640_DP340924.jpg","colorValue":[21,28,14]},{"filename":"1625_DP145928.jpg","colorValue":[22,49,8]},{"filename":"1716_DP312842.jpg","colorValue":[22,45,13]},{"filename":"1685_DT11676.jpg","colorValue":[22,29,13]},{"filename":"1650_DP145397.jpg","colorValue":[24,26,15]},{"filename":"1747_DP287645.jpg","colorValue":[24,18,39]},{"filename":"1747_DP287643.jpg","colorValue":[24,17,39]},{"filename":"1740_DP213772.jpg","colorValue":[24,32,64]},{"filename":"1649_DP143160.jpg","colorValue":[25,35,11]},{"filename":"1658_DP145912.jpg","colorValue":[25,22,11]},{"filename":"1763_DP-12953-001.jpg","colorValue":[25,30,15]},{"filename":"1700_DP-13708-002.jpg","colorValue":[25,26,47]},{"filename":"1628_DT5182.jpg","colorValue":[25,24,24]},{"filename":"1630_DP-17640-001.jpg","colorValue":[25,36,10]},{"filename":"1630_DP-14286-015.jpg","colorValue":[25,40,28]},{"filename":"1624_DT2728.jpg","colorValue":[25,26,17]},{"filename":"1680_DP800479.jpg","colorValue":[25,21,89]},{"filename":"1640_DP145921.jpg","colorValue":[26,25,11]},{"filename":"1647_DT3342.jpg","colorValue":[26,38,79]},{"filename":"1690_DP803093.jpg","colorValue":[26,52,83]},{"filename":"1649_DP120785.jpg","colorValue":[26,36,14]},{"filename":"1784_DP264464.jpg","colorValue":[26,32,13]},{"filename":"1619_DT503.jpg","colorValue":[27,56,13]},{"filename":"1787_DP169648.jpg","colorValue":[27,16,11]},{"filename":"1700_DP807117.jpg","colorValue":[27,32,72]},{"filename":"1660_DP-16323-001.jpg","colorValue":[27,53,10]},{"filename":"1670_DP-14936-010.jpg","colorValue":[27,28,13]},{"filename":"1763_DT209325.jpg","colorValue":[28,9,68]},{"filename":"1627_DT1138.jpg","colorValue":[28,24,47]},{"filename":"1632_DT2821.jpg","colorValue":[28,40,14]},{"filename":"1764_DP-1019-01.jpg","colorValue":[28,19,38]},{"filename":"1655_DP147594.jpg","colorValue":[28,21,12]},{"filename":"1782_DP169215.jpg","colorValue":[28,28,12]},{"filename":"1668_DP161065.jpg","colorValue":[28,19,67]},{"filename":"1611_DT5526.jpg","colorValue":[28,33,22]},{"filename":"1680_DP800480.jpg","colorValue":[28,25,90]},{"filename":"1771_DP339578.jpg","colorValue":[29,29,86]},{"filename":"1745_37.165.104.jpg","colorValue":[29,30,52]},{"filename":"1658_DP832663.jpg","colorValue":[29,18,52]},{"filename":"1740_DP806604.jpg","colorValue":[29,51,86]},{"filename":"1740_DP806603.jpg","colorValue":[29,59,86]},{"filename":"1770_DP807775.jpg","colorValue":[29,18,61]},{"filename":"1660_DP143200.jpg","colorValue":[29,30,14]},{"filename":"1614_DT6682.jpg","colorValue":[29,47,16]},{"filename":"1654_DP145920.jpg","colorValue":[30,33,9]},{"filename":"1648_DP120783.jpg","colorValue":[30,10,20]},{"filename":"1645_DP276131.jpg","colorValue":[30,18,16]},{"filename":"1729_DT9353.jpg","colorValue":[30,2,23]},{"filename":"1780_ep67.187.72.R.jpg","colorValue":[30,21,22]},{"filename":"1661_DP205813_CRD.jpg","colorValue":[30,21,70]},{"filename":"1650_DP145905.jpg","colorValue":[30,39,16]},{"filename":"1740_CT_15046.jpg","colorValue":[30,8,41]},{"filename":"1725_DT1445b.jpg","colorValue":[30,23,36]},{"filename":"1641_DT1450.jpg","colorValue":[30,33,12]},{"filename":"1640_DP143162.jpg","colorValue":[30,13,9]},{"filename":"1710_DP808444.jpg","colorValue":[30,36,77]},{"filename":"1610_DP-12413-001.jpg","colorValue":[30,50,4]},{"filename":"1706_DP356144.jpg","colorValue":[30,20,22]},{"filename":"1640_DT10251.jpg","colorValue":[30,25,9]},{"filename":"1613_DP145940.jpg","colorValue":[30,8,10]},{"filename":"1745_DP800777.jpg","colorValue":[30,2,53]},{"filename":"1615_DP120412.jpg","colorValue":[30,14,42]},{"filename":"1654_DP143155.jpg","colorValue":[30,25,6]},{"filename":"1795_DP162144.jpg","colorValue":[30,16,13]},{"filename":"1758_DP810360.jpg","colorValue":[30,31,85]},{"filename":"1675_DP146507.jpg","colorValue":[30,33,6]},{"filename":"1787_DP169397.jpg","colorValue":[30,42,20]},{"filename":"1747_DT201333.jpg","colorValue":[30,18,44]},{"filename":"1616_DP135205.jpg","colorValue":[30,27,67]},{"filename":"1630_DP807961.jpg","colorValue":[31,33,68]},{"filename":"1747_DT201331.jpg","colorValue":[31,15,46]},{"filename":"1634_DT2737.jpg","colorValue":[31,55,17]},{"filename":"1630_DP805696.jpg","colorValue":[31,27,60]},{"filename":"1658_DP276291.jpg","colorValue":[31,31,67]},{"filename":"1635_DP807905.jpg","colorValue":[31,18,61]},{"filename":"1785_DP320103.jpg","colorValue":[31,28,17]},{"filename":"1727_DP801591.jpg","colorValue":[31,26,78]},{"filename":"1767_DP162151.jpg","colorValue":[31,28,16]},{"filename":"1622_DP123854.jpg","colorValue":[31,38,15]},{"filename":"1638_DP145945.jpg","colorValue":[31,38,13]},{"filename":"1642_DP145922.jpg","colorValue":[31,32,13]},{"filename":"1615_DP801802.jpg","colorValue":[31,33,66]},{"filename":"1767_DP-12954-001.jpg","colorValue":[31,21,21]},{"filename":"1655_DP146485.jpg","colorValue":[32,14,38]},{"filename":"1783_DP123832.jpg","colorValue":[32,16,40]},{"filename":"1750_DR138.jpg","colorValue":[32,14,56]},{"filename":"1621_DT31.jpg","colorValue":[32,23,11]},{"filename":"1679_DT6306.jpg","colorValue":[32,18,63]},{"filename":"1651_DP807963.jpg","colorValue":[32,28,66]},{"filename":"1675_DT3744.jpg","colorValue":[32,29,61]},{"filename":"1608_DP-17641-001.jpg","colorValue":[32,16,16]},{"filename":"1653_DP800375.jpg","colorValue":[32,28,79]},{"filename":"1688_1981_4_1a.jpg","colorValue":[32,28,67]},{"filename":"1675_DP807594.jpg","colorValue":[32,27,63]},{"filename":"1633_DP-14286-013.jpg","colorValue":[32,33,28]},{"filename":"1660_DP160249.jpg","colorValue":[32,23,14]},{"filename":"1600_DP807960.jpg","colorValue":[32,30,68]},{"filename":"1760_DP801590.jpg","colorValue":[32,50,89]},{"filename":"1750_DT8976.jpg","colorValue":[32,22,17]},{"filename":"1645_DT1956.jpg","colorValue":[32,35,11]},{"filename":"1727_DP812116.jpg","colorValue":[32,29,68]},{"filename":"1740_DT11039.jpg","colorValue":[32,7,55]},{"filename":"1756_DP-12952-001.jpg","colorValue":[33,39,15]},{"filename":"1727_DP812117.jpg","colorValue":[33,36,64]},{"filename":"1600_DP-12232-250.jpg","colorValue":[33,38,60]},{"filename":"1667_DP162917.jpg","colorValue":[33,32,51]},{"filename":"1602_DP809075.jpg","colorValue":[33,53,87]},{"filename":"1778_DP169223.jpg","colorValue":[33,23,17]},{"filename":"1767_DP134501.jpg","colorValue":[33,36,30]},{"filename":"1626_DP146489.jpg","colorValue":[33,22,10]},{"filename":"1793_DP800700.jpg","colorValue":[33,43,82]},{"filename":"1635_DP140150.jpg","colorValue":[33,26,58]},{"filename":"1640_DP800590.jpg","colorValue":[33,51,82]},{"filename":"1696_DT200590.jpg","colorValue":[33,32,42]},{"filename":"1727_DP812119.jpg","colorValue":[33,51,88]},{"filename":"1651_DP800372.jpg","colorValue":[33,37,75]},{"filename":"1727_DP801593.jpg","colorValue":[33,33,68]},{"filename":"1662_DP231173.jpg","colorValue":[34,36,62]},{"filename":"1763_DP-13038-001.jpg","colorValue":[34,32,13]},{"filename":"1665_DP231165.jpg","colorValue":[34,37,60]},{"filename":"1760_DT4170.jpg","colorValue":[34,41,45]},{"filename":"1662_DP231177.jpg","colorValue":[34,36,62]},{"filename":"1632_DP800293.jpg","colorValue":[34,38,79]},{"filename":"1791_DP164843.jpg","colorValue":[34,31,15]},{"filename":"1745_DT293615.jpg","colorValue":[34,28,45]},{"filename":"1620_DP-12232-164.jpg","colorValue":[34,26,67]},{"filename":"1641_DP812325.jpg","colorValue":[34,37,70]},{"filename":"1780_DP-13039-001.jpg","colorValue":[34,23,18]},{"filename":"1735_DP213776.jpg","colorValue":[34,25,55]},{"filename":"1735_2002.450.jpg","colorValue":[34,16,48]},{"filename":"1778_DP359324_crd.jpg","colorValue":[34,40,66]},{"filename":"1788_DT1992.jpg","colorValue":[34,15,21]},{"filename":"1727_DP808139.jpg","colorValue":[34,25,82]},{"filename":"1727_DP812113.jpg","colorValue":[34,38,77]},{"filename":"1770_DT5291.jpg","colorValue":[34,23,48]},{"filename":"1709_DP205729_CRD.jpg","colorValue":[34,19,65]},{"filename":"1600_2015_300_44_Burke_website.jpg","colorValue":[34,36,59]},{"filename":"1727_DP812105.jpg","colorValue":[34,44,77]},{"filename":"1710_DP808448.jpg","colorValue":[34,39,80]},{"filename":"1710_DP806462.jpg","colorValue":[34,37,73]},{"filename":"1624_DP143211.jpg","colorValue":[35,27,9]},{"filename":"1715_DP277570.jpg","colorValue":[35,19,55]},{"filename":"1781_DP213753.jpg","colorValue":[35,13,50]},{"filename":"1661_DP146447.jpg","colorValue":[35,33,11]},{"filename":"1727_DP812121.jpg","colorValue":[35,30,83]},{"filename":"1620_DP120563.jpg","colorValue":[35,24,10]},{"filename":"1623_DP146499.jpg","colorValue":[35,35,13]},{"filename":"1720_DP120312.jpg","colorValue":[35,22,69]},{"filename":"1733_DP356133.jpg","colorValue":[35,40,9]},{"filename":"1733_DP251150.jpg","colorValue":[35,40,65]},{"filename":"1625_ep49.145.2.R.jpg","colorValue":[35,50,48]},{"filename":"1634_DP145412.jpg","colorValue":[35,19,25]},{"filename":"1655_DP145947.jpg","colorValue":[35,27,9]},{"filename":"1653_DP145907.jpg","colorValue":[35,26,16]},{"filename":"1650_DP145954.jpg","colorValue":[36,16,25]},{"filename":"1793_DP162138.jpg","colorValue":[36,13,15]},{"filename":"1710_DP804020.jpg","colorValue":[36,28,76]},{"filename":"1630_DP-17487-001.jpg","colorValue":[36,29,10]},{"filename":"1655_DP143157.jpg","colorValue":[36,22,60]},{"filename":"1793_DP140141.jpg","colorValue":[36,38,81]},{"filename":"1768_DP168994.jpg","colorValue":[36,34,14]},{"filename":"1760_DT4577.jpg","colorValue":[36,33,15]},{"filename":"1625_ep49.145.1.R.jpg","colorValue":[36,50,44]},{"filename":"1625_DT5154.jpg","colorValue":[36,36,37]},{"filename":"1653_DP319026.jpg","colorValue":[36,14,7]},{"filename":"1639_DP143161.jpg","colorValue":[36,20,10]},{"filename":"1766_DP820570.jpg","colorValue":[36,33,68]},{"filename":"1753_DP164796.jpg","colorValue":[36,27,37]},{"filename":"1745_DP220939.jpg","colorValue":[36,50,80]},{"filename":"1766_DP820571.jpg","colorValue":[37,40,73]},{"filename":"1695_DP231185.jpg","colorValue":[37,26,48]},{"filename":"1767_2015_300_199_D1_Burke.jpg","colorValue":[37,38,74]},{"filename":"1734_DP-409-001.jpg","colorValue":[37,35,20]},{"filename":"1703_13_220_117_O.jpg","colorValue":[37,7,50]},{"filename":"1672_DT404.jpg","colorValue":[37,43,19]},{"filename":"1747_Wrightsman60.jpg","colorValue":[37,19,62]},{"filename":"1612_DP124701.jpg","colorValue":[37,24,62]},{"filename":"1657_DP136269.jpg","colorValue":[37,12,13]},{"filename":"1625_DT5286.jpg","colorValue":[38,31,12]},{"filename":"1774_DP800976.jpg","colorValue":[38,17,56]},{"filename":"1643_DP226145.jpg","colorValue":[38,23,23]},{"filename":"1667_DP251139.jpg","colorValue":[38,44,63]},{"filename":"1642_DP145918.jpg","colorValue":[38,38,11]},{"filename":"1700_DP-12232-233.jpg","colorValue":[38,8,53]},{"filename":"1760_DT5155.jpg","colorValue":[38,35,40]},{"filename":"1765_DP806408.jpg","colorValue":[38,38,73]},{"filename":"1633_DP-16969-001.jpg","colorValue":[38,17,9]},{"filename":"1630_DT1162.jpg","colorValue":[38,34,45]},{"filename":"1760_DP123933.jpg","colorValue":[39,31,11]},{"filename":"1667_1999.161.jpg","colorValue":[39,37,58]},{"filename":"1787_DP162169.jpg","colorValue":[39,13,21]},{"filename":"1753_DP264499.jpg","colorValue":[39,16,25]},{"filename":"1754_DT200612.jpg","colorValue":[39,22,20]},{"filename":"1784_DP800187.jpg","colorValue":[39,21,74]},{"filename":"1775_DP-12955-001.jpg","colorValue":[39,23,12]},{"filename":"1729_DP159333.jpg","colorValue":[39,36,17]},{"filename":"1679_DP153654_CRD.jpg","colorValue":[39,18,78]},{"filename":"1660_DP146444.jpg","colorValue":[40,21,14]},{"filename":"1792_DT2776.jpg","colorValue":[40,24,15]},{"filename":"1646_DP-14936-013.jpg","colorValue":[40,27,13]},{"filename":"1650_DP-14286-001.jpg","colorValue":[40,22,11]},{"filename":"1745_2003_246_O.jpg","colorValue":[40,24,63]},{"filename":"1648_DT1579.jpg","colorValue":[40,64,13]},{"filename":"1657_DP353257.jpg","colorValue":[40,8,23]},{"filename":"1791_DP277639.jpg","colorValue":[41,14,55]},{"filename":"1765_DP820048.jpg","colorValue":[41,29,80]},{"filename":"1753_DP264494.jpg","colorValue":[41,15,21]},{"filename":"1742_DP145895.jpg","colorValue":[41,17,39]},{"filename":"1665_DP-16333-001.jpg","colorValue":[41,20,16]},{"filename":"1740_DP820507.jpg","colorValue":[41,37,84]},{"filename":"1790_DP821131.jpg","colorValue":[41,18,60]},{"filename":"1669_DP154139.jpg","colorValue":[41,24,65]},{"filename":"1665_DP146455.jpg","colorValue":[42,25,16]},{"filename":"1633_DT5475.jpg","colorValue":[42,17,12]},{"filename":"1642_DP143154.jpg","colorValue":[42,16,21]},{"filename":"1723_64_55_2.JPG","colorValue":[42,32,53]},{"filename":"1786_DP169451.jpg","colorValue":[43,19,41]},{"filename":"1630_DP-14936-011.jpg","colorValue":[44,24,18]},{"filename":"1786_DP169448.jpg","colorValue":[44,8,45]},{"filename":"1658_DP148490.jpg","colorValue":[44,19,16]},{"filename":"1600_LC-2015_300_33ab_001.jpg","colorValue":[45,41,62]},{"filename":"1655_DP146457.jpg","colorValue":[45,21,15]},{"filename":"1723_64_55_1.JPG","colorValue":[46,32,51]},{"filename":"1751_DP105021.jpg","colorValue":[46,19,74]},{"filename":"1787_DP-13040-001.jpg","colorValue":[47,17,10]},{"filename":"1644_DP143174.jpg","colorValue":[47,20,33]},{"filename":"1786_DP103066.jpg","colorValue":[47,6,57]},{"filename":"1789_DP162170.jpg","colorValue":[48,16,18]},{"filename":"1613_DP361123.jpg","colorValue":[48,15,6]},{"filename":"1778_DP167133.jpg","colorValue":[49,11,19]},{"filename":"1650_DP147902.jpg","colorValue":[49,9,63]},{"filename":"1655_DP340180.jpg","colorValue":[49,8,26]},{"filename":"1753_DP164797.jpg","colorValue":[51,14,20]},{"filename":"1725_DT2944.jpg","colorValue":[51,6,22]},{"filename":"1643_DP146480.jpg","colorValue":[52,13,12]},{"filename":"1632_DP116165.jpg","colorValue":[53,13,14]},{"filename":"1700_DP811588.jpg","colorValue":[54,9,57]},{"filename":"1650_DP146458.jpg","colorValue":[54,15,13]},{"filename":"1653_DP143205.jpg","colorValue":[55,6,41]},{"filename":"1746_DP124058.jpg","colorValue":[60,21,17]},{"filename":"1750_DP221050.jpg","colorValue":[60,6,3]},{"filename":"1786_DP169450.jpg","colorValue":[63,9,61]},{"filename":"1785_DP169468.jpg","colorValue":[72,12,48]},{"filename":"1783_DP162149.jpg","colorValue":[75,7,11]},{"filename":"1727_DP812108.jpg","colorValue":[76,6,61]},{"filename":"1750_DP813426.jpg","colorValue":[80,5,55]},{"filename":"1790_DP169218.jpg","colorValue":[81,9,29]},{"filename":"1700_DP-10807-115.jpg","colorValue":[90,3,15]},{"filename":"1600_DP104367.jpg","colorValue":[90,23,9]},{"filename":"1753_DP264496.jpg","colorValue":[100,11,22]},{"filename":"1610_DT10296.jpg","colorValue":[146,12,26]},{"filename":"1717_Wrightsman20.jpg","colorValue":[161,28,76]},{"filename":"1657_DP143177.jpg","colorValue":[165,8,10]},{"filename":"1798_ap60.44.11.jpg","colorValue":[166,10,75]},{"filename":"1798_ap60.44.2.jpg","colorValue":[168,4,55]},{"filename":"1666_DP-13189-002_crd.jpg","colorValue":[180,3,7]},{"filename":"1767_DT1384.jpg","colorValue":[193,9,44]},{"filename":"1603_ep89.15.37.jpg","colorValue":[311,23,18]}]},{"decades":"1800-present","artworks":[{"filename":"1858_ep14.40.816.bw.R.jpg","colorValue":[0,0,73]},{"filename":"1800_14_76_16.jpg","colorValue":[0,0,55]},{"filename":"1800_14_76_15.jpg","colorValue":[0,0,55]},{"filename":"1850_2110.jpg","colorValue":[0,0,73]},{"filename":"1895_ap26.51.jpg","colorValue":[0,0,61]},{"filename":"1850_ep26.100.bw.R.jpg","colorValue":[0,0,26]},{"filename":"1823_1975_268_122.JPG","colorValue":[0,0,67]},{"filename":"1800_14_76_14.JPG","colorValue":[0,0,62]},{"filename":"1891_DT1907.jpg","colorValue":[5,10,75]},{"filename":"1811_DT1803.jpg","colorValue":[17,6,56]},{"filename":"1814_DT2550.jpg","colorValue":[18,24,14]},{"filename":"1860_DT229696.jpg","colorValue":[20,40,20]},{"filename":"1914_DT1487.jpg","colorValue":[22,27,45]},{"filename":"1862_DP-14274-015.jpg","colorValue":[22,43,14]},{"filename":"1871_DT4684.jpg","colorValue":[22,12,42]},{"filename":"1818_DT2138.jpg","colorValue":[22,33,16]},{"filename":"1887_DT2167.jpg","colorValue":[23,37,38]},{"filename":"1870_DP881443.jpg","colorValue":[24,19,65]},{"filename":"1846_DP247630.jpg","colorValue":[25,43,12]},{"filename":"1908_AW_2019_42a_b-037.jpg","colorValue":[26,33,60]},{"filename":"1891_DP139626.jpg","colorValue":[27,7,25]},{"filename":"1868_DP243839.jpg","colorValue":[27,26,18]},{"filename":"1871_DT1911.jpg","colorValue":[27,32,13]},{"filename":"1811_DP169566.jpg","colorValue":[27,47,20]},{"filename":"1807_DP170288.jpg","colorValue":[27,21,16]},{"filename":"1843_DP169610.jpg","colorValue":[27,28,16]},{"filename":"1865_DP-16686-001.jpg","colorValue":[28,47,13]},{"filename":"1862_DP-14936-025.jpg","colorValue":[28,70,8]},{"filename":"1870_DT1918.jpg","colorValue":[29,36,18]},{"filename":"1857_DT1961.jpg","colorValue":[29,75,11]},{"filename":"1863_DP885154.jpg","colorValue":[29,25,64]},{"filename":"1822_DP150998.jpg","colorValue":[29,38,16]},{"filename":"1847_DP169645.jpg","colorValue":[29,20,23]},{"filename":"1873_DP338363.jpg","colorValue":[29,13,52]},{"filename":"1869_DT9827.jpg","colorValue":[29,49,15]},{"filename":"1835_DP164876.jpg","colorValue":[29,16,33]},{"filename":"1858_ep87.24.R.jpg","colorValue":[30,29,57]},{"filename":"1800_14_76_45_02_sf.jpg","colorValue":[30,21,36]},{"filename":"1825_DP213130.jpg","colorValue":[30,32,17]},{"filename":"1866_DP273977.jpg","colorValue":[30,32,65]},{"filename":"1883_DP332016_crd.jpg","colorValue":[30,11,82]},{"filename":"1873_DT1910.jpg","colorValue":[30,28,23]},{"filename":"1817_DP146997.jpg","colorValue":[31,26,49]},{"filename":"1824_DP164869.jpg","colorValue":[31,32,30]},{"filename":"1882_DP241909.jpg","colorValue":[31,33,19]},{"filename":"1800_DP-17561-001.jpg","colorValue":[32,62,4]},{"filename":"1880_ap66.242.22.jpg","colorValue":[32,26,38]},{"filename":"1835_DP805109.jpg","colorValue":[32,18,63]},{"filename":"1821_DP142281.jpg","colorValue":[32,29,62]},{"filename":"1888_DT1947.jpg","colorValue":[32,31,55]},{"filename":"1876_DP-16687-001.jpg","colorValue":[32,25,10]},{"filename":"1892_DP211867.jpg","colorValue":[33,15,56]},{"filename":"1833_DP-15661-002.jpg","colorValue":[33,27,53]},{"filename":"1818_DP836020.jpg","colorValue":[33,46,57]},{"filename":"1853_DP800942.jpg","colorValue":[33,19,81]},{"filename":"1815_DP829468.jpg","colorValue":[33,23,62]},{"filename":"1830_DP809816.jpg","colorValue":[33,6,68]},{"filename":"1857_DP805828.jpg","colorValue":[34,18,59]},{"filename":"1845_DT73.jpg","colorValue":[34,47,79]},{"filename":"1865_DP854869.jpg","colorValue":[34,20,46]},{"filename":"1804_DP-12232-133.jpg","colorValue":[34,30,52]},{"filename":"1812_DP804710.jpg","colorValue":[34,19,56]},{"filename":"1899_DT1559.jpg","colorValue":[35,24,76]},{"filename":"1861_DP-14936-027.jpg","colorValue":[35,33,11]},{"filename":"1882_DT200593.jpg","colorValue":[35,23,67]},{"filename":"1887_DT1502_cropped2.jpg","colorValue":[35,31,54]},{"filename":"1825_DT4626.jpg","colorValue":[35,54,15]},{"filename":"1897_DT1906.jpg","colorValue":[35,12,68]},{"filename":"1869_DT2156.jpg","colorValue":[35,40,49]},{"filename":"1870_DT1564.jpg","colorValue":[36,36,35]},{"filename":"1823_DP162148.jpg","colorValue":[36,24,16]},{"filename":"1858_DP277399.jpg","colorValue":[36,18,61]},{"filename":"1856_DT283482.jpg","colorValue":[36,24,47]},{"filename":"1854_DP800428.jpg","colorValue":[36,25,69]},{"filename":"1869_DP-16589-001.jpg","colorValue":[37,19,13]},{"filename":"1877_DP230590.jpg","colorValue":[37,47,79]},{"filename":"1830_DP800444.jpg","colorValue":[37,24,75]},{"filename":"1862_DT859.jpg","colorValue":[37,12,22]},{"filename":"1835_DP-14346-001.jpg","colorValue":[37,25,10]},{"filename":"1840_DP-14527-002.jpg","colorValue":[37,29,52]},{"filename":"1863_DP803693.jpg","colorValue":[37,38,88]},{"filename":"1815_DP806714.jpg","colorValue":[37,27,76]},{"filename":"1830_DP277632.jpg","colorValue":[37,23,68]},{"filename":"1865_DP801244.jpg","colorValue":[37,11,61]},{"filename":"1868_DP354141.jpg","colorValue":[37,22,26]},{"filename":"1834_DP-12232-083.jpg","colorValue":[38,16,10]},{"filename":"1891_DP-14201-043.jpg","colorValue":[38,22,19]},{"filename":"1853_DP827272.jpg","colorValue":[38,21,56]},{"filename":"1843_DP821057.jpg","colorValue":[38,30,69]},{"filename":"1800_DT822.jpg","colorValue":[39,18,19]},{"filename":"1830_DP850230.jpg","colorValue":[39,27,77]},{"filename":"1847_DP860361.jpg","colorValue":[39,16,39]},{"filename":"1851_DT1967.jpg","colorValue":[40,43,27]},{"filename":"1824_2015_300_94_D1_Burke.jpg","colorValue":[40,46,82]},{"filename":"1826_DP274250.jpg","colorValue":[41,15,21]},{"filename":"1832_DP803842.jpg","colorValue":[41,33,78]},{"filename":"1810_DT4026.jpg","colorValue":[41,31,19]},{"filename":"1865_DT1566.jpg","colorValue":[42,30,30]},{"filename":"1869_DP124093.jpg","colorValue":[42,23,40]},{"filename":"1878_DT249052.jpg","colorValue":[42,62,82]},{"filename":"1890_36_100_101_O1.jpg","colorValue":[43,13,48]},{"filename":"1800_DP150997.jpg","colorValue":[43,9,60]},{"filename":"1832_DP274261.jpg","colorValue":[43,15,41]},{"filename":"1857_DP829460.jpg","colorValue":[44,20,78]},{"filename":"1853_DP808071.jpg","colorValue":[44,15,43]},{"filename":"1890_DT7098.jpg","colorValue":[44,9,23]},{"filename":"1872_DT1982.jpg","colorValue":[44,23,32]},{"filename":"1871_DT1565.jpg","colorValue":[45,23,31]},{"filename":"1840_DP-13360-001.jpg","colorValue":[46,26,64]},{"filename":"1820_DT4937.jpg","colorValue":[49,26,38]},{"filename":"1846_ap63.200.5.jpg","colorValue":[51,12,21]},{"filename":"1899_DP-14936-037.jpg","colorValue":[52,6,54]},{"filename":"1852_DT44.jpg","colorValue":[52,20,24]},{"filename":"1884_DP259921.jpg","colorValue":[53,9,37]},{"filename":"1833_DP143197.jpg","colorValue":[54,9,45]},{"filename":"1821_2001_561_2.jpg","colorValue":[55,17,45]},{"filename":"1881_DT2165.jpg","colorValue":[56,49,28]},{"filename":"1881_DP161238.jpg","colorValue":[56,14,41]},{"filename":"1891_DT1025.jpg","colorValue":[60,10,40]},{"filename":"1899_DT5581.jpg","colorValue":[60,8,71]},{"filename":"1823_DP882756.jpg","colorValue":[60,8,69]},{"filename":"1887_DP229743.jpg","colorValue":[65,6,38]},{"filename":"1879_DP-14201-049.jpg","colorValue":[67,10,17]},{"filename":"1818_DT1997.jpg","colorValue":[70,9,13]},{"filename":"1862_DP302937.jpg","colorValue":[71,26,16]},{"filename":"1874_DT1554.jpg","colorValue":[78,7,55]},{"filename":"1890_DP124808.jpg","colorValue":[90,13,53]},{"filename":"1811_DP813425.jpg","colorValue":[93,4,59]},{"filename":"1853_DP267027.jpg","colorValue":[96,8,24]},{"filename":"1888_DT1396.jpg","colorValue":[126,11,18]},{"filename":"1867_DT1931.jpg","colorValue":[139,12,26]},{"filename":"1825_DP809528.jpg","colorValue":[140,3,65]},{"filename":"1899_DP140858.jpg","colorValue":[150,8,24]},{"filename":"1885_DT1492.jpg","colorValue":[165,11,35]},{"filename":"1851_DT717.jpg","colorValue":[168,9,22]},{"filename":"1918_2018.212.jpg","colorValue":[170,5,22]},{"filename":"1872_DP-14936-041.jpg","colorValue":[184,7,43]},{"filename":"1890_DP231550.jpg","colorValue":[195,3,25]},{"filename":"1851_APS1047.jpg","colorValue":[202,24,9]},{"filename":"1869_DT1541.jpg","colorValue":[204,24,48]},{"filename":"1860_DT225534.jpg","colorValue":[240,1,73]},{"filename":"1887_DP375450_cropped.jpg","colorValue":[312,4,25]}]}]