{"objectID":21997,"isHighlight":false,"accessionNumber":"04.3.274","isPublicDomain":true,"primaryImage":"https://images.metmuseum.org/CRDImages/aa/original/DT200138.jpg","primaryImageSmall":"https://images.metmuseum.org/CRDImages/aa/web-large/DT200138.jpg","additionalImages":[],"constituents":null,"department":"Arms and Armor","objectName":"Foot-combat helm","title":"Foot-Combat Helm of Sir Giles Capel (1485–1556)","culture":"possibly British","period":"","dynasty":"","reign":"","portfolio":"","artistRole":"","artistPrefix":"","artistDisplayName":"","artistDisplayBio":"","artistSuffix":"","artistAlphaSort":"","artistNationality":"","artistBeginDate":"","artistEndDate":"","objectDate":"ca. 1510","objectBeginDate":1485,"objectEndDate":1535,"medium":"Steel","dimensions":"H. 17 1/2 in. (44.4 cm); W. 11 1/4 in. (28.6 cm); D. 9 1/2 in. (24.1 cm); Wt. 13 lb. 8 oz. (6123 g)","creditLine":"Rogers Fund, 1904","geographyType":"Country of Origin","city":"","state":"","county":"","country":"possibly England","region":"","subregion":"","locale":"","locus":"","excavation":"","river":"","classification":"Helmets","rightsAndReproduction":"","linkResource":"","metadataDate":"2019-08-02T04:37:44.223Z","repository":"Metropolitan Museum of Art, New York, NY","objectURL":"https://www.metmuseum.org/art/collection/search/21997","tags":[]}