{"objectID":233022,"isHighlight":false,"accessionNumber":"1974.356.119b–d","isPublicDomain":true,"primaryImage":"https://images.metmuseum.org/CRDImages/es/original/DP17335_1974.356.119B.jpg","primaryImageSmall":"https://images.metmuseum.org/CRDImages/es/web-large/DP17335_1974.356.119B.jpg","additionalImages":["https://images.metmuseum.org/CRDImages/es/original/DP17337_1974.356.119D.jpg","https://images.metmuseum.org/CRDImages/es/original/DP17329_1974.356.119B.jpg","https://images.metmuseum.org/CRDImages/es/original/DP105736.jpg","https://images.metmuseum.org/CRDImages/es/original/DP105737.jpg"],"constituents":null,"department":"European Sculpture and Decorative Arts","objectName":"Upholstery panel","title":"Upholstery panels for an armchair","culture":"","period":"","dynasty":"","reign":"","portfolio":"","artistRole":"","artistPrefix":"","artistDisplayName":"","artistDisplayBio":"","artistSuffix":"","artistAlphaSort":"","artistNationality":"","artistBeginDate":"","artistEndDate":"","objectDate":"ca. 1764–64","objectBeginDate":1759,"objectEndDate":1769,"medium":"Silk, painted","dimensions":"b: 26 x 21\r\nc: 55 x 24\r\nd: 28 x 25 1/2","creditLine":"The Lesley and Emma Sheafer Collection, Bequest of Emma A. Sheafer, 1973","geographyType":"","city":"","state":"","county":"","country":"","region":"","subregion":"","locale":"","locus":"","excavation":"","river":"","classification":"Textiles-Painted","rightsAndReproduction":"","linkResource":"","metadataDate":"2019-09-04T04:43:07.113Z","repository":"Metropolitan Museum of Art, New York, NY","objectURL":"https://www.metmuseum.org/art/collection/search/233022","tags":["Butterflies","Flowers","Leaves"]}