{"objectID":324853,"isHighlight":false,"accessionNumber":"59.41.23","isPublicDomain":true,"primaryImage":"https://images.metmuseum.org/CRDImages/an/original/DP222633.jpg","primaryImageSmall":"https://images.metmuseum.org/CRDImages/an/web-large/DP222633.jpg","additionalImages":[],"constituents":null,"department":"Ancient Near Eastern Art","objectName":"Sculpture","title":"Figurine","culture":"Parthian","period":"Parthian","dynasty":"","reign":"","portfolio":"","artistRole":"","artistPrefix":"","artistDisplayName":"","artistDisplayBio":"","artistSuffix":"","artistAlphaSort":"","artistNationality":"","artistBeginDate":"","artistEndDate":"","objectDate":"ca. 150 B.C.","objectBeginDate":-150,"objectEndDate":-150,"medium":"Ceramic, paint","dimensions":"H. 6 3/4 x W. 2 1/16 x D. 4 9/16 in. (17.1 x 5.3 x 11.5 cm)","creditLine":"Rogers Fund, 1959","geographyType":"","city":"","state":"","county":"","country":"","region":"Mesopotamia","subregion":"Nippur","locale":"","locus":"","excavation":"","river":"","classification":"Ceramics-Sculpture","rightsAndReproduction":"","linkResource":"","metadataDate":"2019-08-22T03:00:43.77Z","repository":"Metropolitan Museum of Art, New York, NY","objectURL":"https://www.metmuseum.org/art/collection/search/324853","tags":["Human Figures","Animals"]}