{"objectID":325144,"isHighlight":false,"accessionNumber":"61.100.10","isPublicDomain":true,"primaryImage":"https://images.metmuseum.org/CRDImages/an/original/DT5092.jpg","primaryImageSmall":"https://images.metmuseum.org/CRDImages/an/web-large/DT5092.jpg","additionalImages":[],"constituents":null,"department":"Ancient Near Eastern Art","objectName":"Pin","title":"Pin in the form of a lion","culture":"Iran","period":"Iron Age II","dynasty":"","reign":"","portfolio":"","artistRole":"","artistPrefix":"","artistDisplayName":"","artistDisplayBio":"","artistSuffix":"","artistAlphaSort":"","artistNationality":"","artistBeginDate":"","artistEndDate":"","objectDate":"ca. 9th century B.C.","objectBeginDate":-900,"objectEndDate":-800,"medium":"Bronze, iron","dimensions":"2.28 x 5 in. (5.79 x 12.7 cm)","creditLine":"Purchase, Mrs. Constantine Sidamon-Eristoff Gift, 1961","geographyType":"","city":"","state":"","county":"","country":"","region":"Iran","subregion":"Hasanlu","locale":"","locus":"","excavation":"","river":"","classification":"Metalwork-Ornaments","rightsAndReproduction":"","linkResource":"","metadataDate":"2019-02-01T10:50:49.477Z","repository":"Metropolitan Museum of Art, New York, NY","objectURL":"https://www.metmuseum.org/art/collection/search/325144","tags":["Pins","Lions"]}