{"objectID":35772,"isHighlight":false,"accessionNumber":"14.25.709a–p; 21.139.1a–x,.8,.12; 1984.356","isPublicDomain":true,"primaryImage":"https://images.metmuseum.org/CRDImages/aa/original/DP-12882-001.jpg","primaryImageSmall":"https://images.metmuseum.org/CRDImages/aa/web-large/DP-12882-001.jpg","additionalImages":["https://images.metmuseum.org/CRDImages/aa/original/DP-12882-002.jpg","https://images.metmuseum.org/CRDImages/aa/original/DP-12882-003.jpg","https://images.metmuseum.org/CRDImages/aa/original/51164.jpg","https://images.metmuseum.org/CRDImages/aa/original/51165.jpg","https://images.metmuseum.org/CRDImages/aa/original/51166.jpg"],"constituents":null,"department":"Arms and Armor","objectName":"Armor for man and horse","title":"Armor for Man and Horse","culture":"Italian, Milan and Brescia","period":"","dynasty":"","reign":"","portfolio":"","artistRole":"","artistPrefix":"","artistDisplayName":"","artistDisplayBio":"","artistSuffix":"","artistAlphaSort":"","artistNationality":"","artistBeginDate":"","artistEndDate":"","objectDate":"man's armor, ca. 1570 and later; horse armor, ca. 1580–90 and later","objectBeginDate":1545,"objectEndDate":1900,"medium":"Steel, leather, copper alloy, textile","dimensions":"as mounted, H. of horse armor 75 1/2 in. (191.8 cm); L. of horse armor 90 in. (228.6 cm); W. of horse armor 30 in. (76.2 cm); Wt. of horse armor including saddle 93 lb. 1 oz. (42.2 kg); Wt. of man's armor approx. 37 lb. (16.78 kg)","creditLine":"man's armor: Gift of William H. Riggs, 1913; horse armor, bit, rear plate of saddle: Fletcher Fund, 1921; part of a greave: Rogers Fund, 1984","geographyType":"Country of Origin","city":"Milan and Brescia","state":"","county":"","country":"Italy","region":"","subregion":"","locale":"","locus":"","excavation":"","river":"","classification":"Armor for Horse and Man","rightsAndReproduction":"","linkResource":"","metadataDate":"2019-07-21T03:00:42.11Z","repository":"Metropolitan Museum of Art, New York, NY","objectURL":"https://www.metmuseum.org/art/collection/search/35772","tags":[]}