{"objectID":471767,"isHighlight":false,"accessionNumber":"56.171.106","isPublicDomain":true,"primaryImage":"https://images.metmuseum.org/CRDImages/cl/original/cdi56-171-106.jpg","primaryImageSmall":"https://images.metmuseum.org/CRDImages/cl/web-large/cdi56-171-106.jpg","additionalImages":["https://images.metmuseum.org/CRDImages/cl/original/cdi56-171-106s2.jpg"],"constituents":null,"department":"The Cloisters","objectName":"Dish","title":"Dish","culture":"Spanish","period":"","dynasty":"","reign":"","portfolio":"","artistRole":"","artistPrefix":"","artistDisplayName":"","artistDisplayBio":"","artistSuffix":"","artistAlphaSort":"","artistNationality":"","artistBeginDate":"","artistEndDate":"","objectDate":"1420–1450","objectBeginDate":1420,"objectEndDate":1450,"medium":"Tin-glazed earthenware","dimensions":"Overall: 17 3/8 in. (44.1 cm)","creditLine":"The Cloisters Collection, 1956","geographyType":"Made in","city":"probably Manises","state":"Valencia","county":"","country":"Spain","region":"","subregion":"","locale":"","locus":"","excavation":"","river":"","classification":"Ceramics","rightsAndReproduction":"","linkResource":"","metadataDate":"2019-05-24T04:46:04.46Z","repository":"Metropolitan Museum of Art, New York, NY","objectURL":"https://www.metmuseum.org/art/collection/search/471767","tags":["Birds","Coat of Arms","Dishes"]}