{"objectID":50806,"isHighlight":false,"accessionNumber":"1979.409","isPublicDomain":true,"primaryImage":"https://images.metmuseum.org/CRDImages/as/original/ASA210.jpg","primaryImageSmall":"https://images.metmuseum.org/CRDImages/as/web-large/ASA210.jpg","additionalImages":["https://images.metmuseum.org/CRDImages/as/original/217906.jpg","https://images.metmuseum.org/CRDImages/as/original/RT792C.jpg"],"constituents":null,"department":"Asian Art","objectName":"Sashiko kimono","title":"Sashiko Kimono","culture":"Japan","period":"Meiji period (1868–1912)","dynasty":"","reign":"","portfolio":"","artistRole":"","artistPrefix":"","artistDisplayName":"","artistDisplayBio":"","artistSuffix":"","artistAlphaSort":"","artistNationality":"","artistBeginDate":"","artistEndDate":"","objectDate":"mid-19th century","objectBeginDate":1834,"objectEndDate":1866,"medium":"Indigo-dyed plain-weave cotton, quilted and embroidered with white cotton thread","dimensions":"Overall: 55 1/2 x 45 in. (141 x 114.3 cm)","creditLine":"Purchase, Mrs. Jackson Burke Gift, 1979","geographyType":"","city":"","state":"","county":"","country":"","region":"","subregion":"","locale":"","locus":"","excavation":"","river":"","classification":"Costumes","rightsAndReproduction":"","linkResource":"","metadataDate":"2019-05-23T10:39:17.207Z","repository":"Metropolitan Museum of Art, New York, NY","objectURL":"https://www.metmuseum.org/art/collection/search/50806","tags":["Robes"]}